django_prefix_id-1.0.1.dist-info/licenses/LICENSE
prefix_id/__init__.py
prefix_id/base62.py
prefix_id/field.py
django_prefix_id-1.0.1.dist-info/METADATA
django_prefix_id-1.0.1.dist-info/WHEEL
django_prefix_id-1.0.1.dist-info/top_level.txt
django_prefix_id-1.0.1.dist-info/RECORD
