Metadata-Version: 2.4
Name: django-prefix-id
Version: 1.0.1
Summary: A simple prefix ID Django model field, using UUID to Base62 encoding.
Author-email: James Addison <addi00@gmail.com>
Project-URL: Homepage, https://github.com/jaddison/django-prefix-id
Project-URL: Bug Tracker, https://github.com/jaddison/django-prefix-id/issues
Classifier: Programming Language :: Python :: 3
Classifier: License :: OSI Approved :: MIT License
Classifier: Operating System :: OS Independent
Classifier: Intended Audience :: Developers
Classifier: Topic :: Software Development :: Libraries :: Python Modules
Classifier: Environment :: Web Environment
Classifier: Framework :: Django
Requires-Python: >=3.8
License-File: LICENSE
Requires-Dist: django
Dynamic: license-file
